__init__.py
pytest_fixture_timing.py
pytest_fixture_timing-0.0.2.dist-info/METADATA
pytest_fixture_timing-0.0.2.dist-info/WHEEL
pytest_fixture_timing-0.0.2.dist-info/entry_points.txt
pytest_fixture_timing-0.0.2.dist-info/top_level.txt
pytest_fixture_timing-0.0.2.dist-info/RECORD
