Metadata-Version: 2.4
Name: pytest-fixture-timing
Version: 0.0.2
Summary: Tiny plugin to report total duration per fixture
Requires-Python: >=3.10
Requires-Dist: pytest>=7.0
